phoila/__init__.py
phoila/_version.py
phoila/app.py
phoila/app_config.py
phoila/commands.py
phoila/lab_handlers.py
phoila/server_extension.py
phoila/serverapp.py
phoila/voila_handlers.py
phoila/templates/login.html
phoila/templates/logout.html
phoila/tests/__init__.py
phoila/tests/conftest.py
phoila-0.3.0.data/data/etc/jupyter/jupyter_notebook_config.d/phoila.json
phoila-0.3.0.data/data/share/jupyter/phoila/extensions/phoila-0.3.0.tgz
phoila-0.3.0.data/data/share/jupyter/voila/templates/phoila/nbconvert_templates/voila.tpl
phoila-0.3.0.dist-info/LICENSE.txt
phoila-0.3.0.dist-info/METADATA
phoila-0.3.0.dist-info/WHEEL
phoila-0.3.0.dist-info/entry_points.txt
phoila-0.3.0.dist-info/top_level.txt
phoila-0.3.0.dist-info/RECORD
