Metadata-Version: 2.1
Name: phoila
Version: 0.3.0
Summary: A Phosphor wrapper for Voila
Home-page: https://github.com/vidartf/phoila
Author: Vidar Tonaas Fauske
Author-email: vidartf@gmail.com
License: BSD
Keywords: Jupyter,Widgets,IPython
Platform: Linux
Platform: Mac OS X
Platform: Windows
Classifier: Intended Audience :: Developers
Classifier: Intended Audience :: Science/Research
Classifier: License :: OSI Approved :: BSD License
Classifier: Programming Language :: Python
Classifier: Programming Language :: Python :: 3
Classifier: Programming Language :: Python :: 3.4
Classifier: Programming Language :: Python :: 3.5
Classifier: Programming Language :: Python :: 3.6
Classifier: Programming Language :: Python :: 3.7
Classifier: Framework :: Jupyter
Requires-Dist: ipywidgets (>=7.0.0)
Requires-Dist: jupyter-server (>=0.1.1)
Requires-Dist: jupyterlab (>=1.1.0)
Requires-Dist: voila (>=0.1.10)
Provides-Extra: test
Requires-Dist: pytest (>=3.6) ; extra == 'test'
Requires-Dist: pytest-cov ; extra == 'test'
